avocato/__init__.py
avocato/exceptions.py
avocato/fields.py
avocato/serializer.py
avocato/validators.py
avocato-0.1.0.dist-info/LICENSE
avocato-0.1.0.dist-info/METADATA
avocato-0.1.0.dist-info/WHEEL
avocato-0.1.0.dist-info/top_level.txt
avocato-0.1.0.dist-info/RECORD
