Metadata-Version: 2.1
Name: avocato
Version: 0.1.0
Summary: Simple and fast object serialization.
Home-page: https://github.com/tsifrer/avocato
Author: Tomaz Sifrer
Author-email: tomazz.sifrer@gmail.com
License: MIT
Keywords: serialization,deserialization,validation,rest,json,api,fast
Platform: UNKNOWN
Classifier: Intended Audience :: Developers
Classifier: License :: OSI Approved :: MIT License
Classifier: Natural Language :: English
Classifier: Programming Language :: Python :: 3
Classifier: Programming Language :: Python :: 3.5
Classifier: Programming Language :: Python :: 3.6
Classifier: Programming Language :: Python :: 3.7
Classifier: Programming Language :: Python :: Implementation :: CPython
Classifier: Programming Language :: Python :: Implementation :: PyPy
Provides-Extra: django
Requires-Dist: django (>=2.1.5) ; extra == 'django'
Requires-Dist: psycopg2-binary (>=2.7.6.1) ; extra == 'django'
Provides-Extra: peewee
Requires-Dist: peewee (>=3.8.1) ; extra == 'peewee'
Requires-Dist: psycopg2-binary (>=2.7.6.1) ; extra == 'peewee'
